llm_magics/__init__.py
llm_magics/client.py
llm_magics/ipython.py
llm_magics/rendering.py
llm_magics-1.2.1.dist-info/LICENSE
llm_magics-1.2.1.dist-info/METADATA
llm_magics-1.2.1.dist-info/WHEEL
llm_magics-1.2.1.dist-info/top_level.txt
llm_magics-1.2.1.dist-info/RECORD
