Metadata-Version: 2.1
Name: llm_magics
Version: 1.2.1
Summary: LLM Magics for Ipython created by kmkolasinski
Home-page: https://github.com/kmkolasinski/llm_magics/
Author: kmkolasinski
License-File: LICENSE
Requires-Dist: openai~=1.41.1
Provides-Extra: test
Requires-Dist: gitchangelog; extra == "test"
Requires-Dist: pytest; extra == "test"
